sispm/__init__.py
pysispm-0.6.dist-info/LICENSE.txt
pysispm-0.6.dist-info/METADATA
pysispm-0.6.dist-info/WHEEL
pysispm-0.6.dist-info/top_level.txt
pysispm-0.6.dist-info/RECORD
