Metadata-Version: 2.1
Name: pysispm
Version: 0.6
Summary: Library for EnerGenie USB controlled powerstrips
Home-page: https://github.com/xypron/pysispm
Author: Heinrich Schuchardt
Author-email: xypron.glpk@gmx.de
License: BSD
Platform: UNKNOWN
Classifier: Development Status :: 4 - Beta
Classifier: Intended Audience :: Developers
Classifier: License :: OSI Approved :: BSD License
Classifier: Operating System :: POSIX
Classifier: Programming Language :: Python :: 3
Classifier: Topic :: System :: Hardware :: Hardware Drivers
Requires-Dist: pyusb (>=1.0.0a)
